{"version":1,"content":"{\"storage\":{\"cpp.1.lastSessionDate\":{\"version\":1,\"value\":\"Sat Aug 22 2020\"},\"cpp.1.sessionCount\":{\"version\":1,\"value\":\"20\"},\"java.2.lastSessionDate\":{\"version\":1,\"value\":\"Sat Aug 22 2020\"},\"java.2.sessionCount\":{\"version\":1,\"value\":\"20\"},\"javascript.1.lastSessionDate\":{\"version\":1,\"value\":\"Sat Aug 22 2020\"},\"javascript.1.sessionCount\":{\"version\":1,\"value\":\"20\"},\"nps/isCandidate\":{\"version\":1,\"value\":\"false\"},\"nps/lastSessionDate\":{\"version\":1,\"value\":\"Tue Jul 14 2020\"},\"nps/sessionCount\":{\"version\":1,\"value\":\"9\"},\"nps/skipVersion\":{\"version\":1,\"value\":\"1.47.0\"},\"typescript.1.lastSessionDate\":{\"version\":1,\"value\":\"Sat Aug 22 2020\"},\"typescript.1.sessionCount\":{\"version\":1,\"value\":\"20\"},\"workbench.activity.pinnedViewlets2\":{\"version\":1,\"value\":\"[{\\\"id\\\":\\\"workbench.view.explorer\\\",\\\"pinned\\\":true,\\\"visible\\\":true,\\\"order\\\":0},{\\\"id\\\":\\\"workbench.view.search\\\",\\\"pinned\\\":true,\\\"visible\\\":true,\\\"order\\\":1},{\\\"id\\\":\\\"workbench.view.scm\\\",\\\"pinned\\\":true,\\\"visible\\\":true,\\\"order\\\":2},{\\\"id\\\":\\\"workbench.view.debug\\\",\\\"pinned\\\":true,\\\"visible\\\":true,\\\"order\\\":2},{\\\"id\\\":\\\"workbench.view.remote\\\",\\\"pinned\\\":true,\\\"visible\\\":true,\\\"order\\\":4},{\\\"id\\\":\\\"workbench.view.extensions\\\",\\\"pinned\\\":true,\\\"visible\\\":true,\\\"order\\\":4},{\\\"id\\\":\\\"workbench.view.extension.references-view\\\",\\\"pinned\\\":true,\\\"visible\\\":false,\\\"order\\\":7},{\\\"id\\\":\\\"workbench.view.extension.latex\\\",\\\"pinned\\\":true,\\\"visible\\\":true,\\\"order\\\":8},{\\\"id\\\":\\\"workbench.view.extension.liveshare\\\",\\\"pinned\\\":true,\\\"visible\\\":true,\\\"order\\\":9},{\\\"id\\\":\\\"workbench.view.extension.chatActivityViewSlack\\\",\\\"pinned\\\":true,\\\"visible\\\":false,\\\"order\\\":10},{\\\"id\\\":\\\"workbench.view.extension.chatActivityViewDiscord\\\",\\\"pinned\\\":true,\\\"visible\\\":false,\\\"order\\\":11},{\\\"id\\\":\\\"workbench.view.sync\\\",\\\"pinned\\\":true,\\\"visible\\\":false}]\"},\"workbench.explorer.views.state.hidden\":{\"version\":1,\"value\":\"[{\\\"id\\\":\\\"outline\\\",\\\"isHidden\\\":false},{\\\"id\\\":\\\"timeline\\\",\\\"isHidden\\\":false},{\\\"id\\\":\\\"workbench.explorer.openEditorsView\\\",\\\"isHidden\\\":false},{\\\"id\\\":\\\"workbench.explorer.emptyView\\\",\\\"isHidden\\\":false},{\\\"id\\\":\\\"npm\\\",\\\"isHidden\\\":false},{\\\"id\\\":\\\"workbench.explorer.fileView\\\",\\\"isHidden\\\":false},{\\\"id\\\":\\\"liveshare.session.explorer\\\",\\\"isHidden\\\":false}]\"},\"workbench.panel.markers.hidden\":{\"version\":1,\"value\":\"[{\\\"id\\\":\\\"workbench.panel.markers.view\\\",\\\"isHidden\\\":false}]\"},\"workbench.panel.output.hidden\":{\"version\":1,\"value\":\"[{\\\"id\\\":\\\"workbench.panel.output\\\",\\\"isHidden\\\":false}]\"},\"workbench.panel.pinnedPanels\":{\"version\":1,\"value\":\"[{\\\"id\\\":\\\"workbench.panel.markers\\\",\\\"name\\\":\\\"Problems\\\",\\\"pinned\\\":true,\\\"order\\\":0,\\\"visible\\\":true},{\\\"id\\\":\\\"workbench.panel.output\\\",\\\"name\\\":\\\"Output\\\",\\\"pinned\\\":true,\\\"order\\\":1,\\\"visible\\\":true},{\\\"id\\\":\\\"workbench.panel.repl\\\",\\\"name\\\":\\\"Debug Console\\\",\\\"pinned\\\":true,\\\"order\\\":2,\\\"visible\\\":true},{\\\"id\\\":\\\"workbench.panel.terminal\\\",\\\"name\\\":\\\"Terminal\\\",\\\"pinned\\\":true,\\\"order\\\":3,\\\"visible\\\":true},{\\\"id\\\":\\\"refactorPreview\\\",\\\"name\\\":\\\"Refactor Preview\\\",\\\"pinned\\\":true,\\\"visible\\\":false}]\"},\"workbench.panel.repl.hidden\":{\"version\":1,\"value\":\"[{\\\"id\\\":\\\"workbench.panel.repl.view\\\",\\\"isHidden\\\":false}]\"},\"workbench.panel.terminal.hidden\":{\"version\":1,\"value\":\"[{\\\"id\\\":\\\"workbench.panel.terminal\\\",\\\"isHidden\\\":false}]\"},\"workbench.scm.views.state.hidden\":{\"version\":1,\"value\":\"[{\\\"id\\\":\\\"workbench.scm\\\",\\\"isHidden\\\":false},{\\\"id\\\":\\\"scm.mainPane\\\",\\\"isHidden\\\":false},{\\\"id\\\":\\\"scm:repository:1030676787\\\",\\\"isHidden\\\":false},{\\\"id\\\":\\\"scm:repository:-944183021\\\",\\\"isHidden\\\":false},{\\\"id\\\":\\\"scm:repository:1815267739\\\",\\\"isHidden\\\":false},{\\\"id\\\":\\\"scm:repository:-519673833\\\",\\\"isHidden\\\":false},{\\\"id\\\":\\\"scm:repository:664726321\\\",\\\"isHidden\\\":false},{\\\"id\\\":\\\"scm:repository:1409701161\\\",\\\"isHidden\\\":false},{\\\"id\\\":\\\"scm:repository:885892104\\\",\\\"isHidden\\\":false},{\\\"id\\\":\\\"scm:repository:-553541460\\\",\\\"isHidden\\\":false},{\\\"id\\\":\\\"scm:repository:-1374161647\\\",\\\"isHidden\\\":false},{\\\"id\\\":\\\"scm:repository:1582023852\\\",\\\"isHidden\\\":false},{\\\"id\\\":\\\"scm:repository:-180194292\\\",\\\"isHidden\\\":false},{\\\"id\\\":\\\"scm:repository:289241979\\\",\\\"isHidden\\\":false}]\"},\"workbench.view.debug.state.hidden\":{\"version\":1,\"value\":\"[{\\\"id\\\":\\\"workbench.debug.welcome\\\",\\\"isHidden\\\":false},{\\\"id\\\":\\\"workbench.debug.variablesView\\\",\\\"isHidden\\\":false},{\\\"id\\\":\\\"workbench.debug.watchExpressionsView\\\",\\\"isHidden\\\":false},{\\\"id\\\":\\\"workbench.debug.callStackView\\\",\\\"isHidden\\\":false},{\\\"id\\\":\\\"workbench.debug.loadedScriptsView\\\",\\\"isHidden\\\":false},{\\\"id\\\":\\\"workbench.debug.breakPointsView\\\",\\\"isHidden\\\":false},{\\\"id\\\":\\\"jsBrowserBreakpoints\\\",\\\"isHidden\\\":false}]\"},\"workbench.view.extension.latex.state.hidden\":{\"version\":1,\"value\":\"[{\\\"id\\\":\\\"latex-commands\\\",\\\"isHidden\\\":false},{\\\"id\\\":\\\"latex-structure\\\",\\\"isHidden\\\":false}]\"},\"workbench.view.extension.liveshare.state.hidden\":{\"version\":1,\"value\":\"[{\\\"id\\\":\\\"liveshare.session\\\",\\\"isHidden\\\":false},{\\\"id\\\":\\\"liveshare.plannedSessions\\\",\\\"isHidden\\\":false},{\\\"id\\\":\\\"liveshare.contacts\\\",\\\"isHidden\\\":false},{\\\"id\\\":\\\"liveshare.help\\\",\\\"isHidden\\\":false}]\"},\"workbench.view.extensions.state.hidden\":{\"version\":1,\"value\":\"[{\\\"id\\\":\\\"extensions.enabledExtensionList\\\",\\\"isHidden\\\":false},{\\\"id\\\":\\\"extensions.popularExtensionsList\\\",\\\"isHidden\\\":false},{\\\"id\\\":\\\"extensions.enabledExtensionList2\\\",\\\"isHidden\\\":false},{\\\"id\\\":\\\"extensions.workspaceRecommendedList\\\",\\\"isHidden\\\":false},{\\\"id\\\":\\\"extensions.vscode-local.default\\\",\\\"isHidden\\\":false},{\\\"id\\\":\\\"extensions.recommendedList\\\",\\\"isHidden\\\":false},{\\\"id\\\":\\\"extensions.otherrecommendedList\\\",\\\"isHidden\\\":false},{\\\"id\\\":\\\"extensions.disabledExtensionList\\\",\\\"isHidden\\\":false},{\\\"id\\\":\\\"extensions.disabledExtensionList2\\\",\\\"isHidden\\\":false},{\\\"id\\\":\\\"extensions.listView\\\",\\\"isHidden\\\":false},{\\\"id\\\":\\\"extensions.builtInExtensionsList\\\",\\\"isHidden\\\":false},{\\\"id\\\":\\\"extensions.builtInBasicsExtensionsList\\\",\\\"isHidden\\\":false},{\\\"id\\\":\\\"extensions.builtInThemesExtensionsList\\\",\\\"isHidden\\\":false},{\\\"id\\\":\\\"extensions.vscode-local.installed\\\",\\\"isHidden\\\":false},{\\\"id\\\":\\\"extensions.vscode-local.outdated\\\",\\\"isHidden\\\":false},{\\\"id\\\":\\\"extensions.ssh-remote+bigred.default\\\",\\\"isHidden\\\":false},{\\\"id\\\":\\\"extensions.ssh-remote+bigred.installed\\\",\\\"isHidden\\\":false},{\\\"id\\\":\\\"extensions.ssh-remote+bigred.outdated\\\",\\\"isHidden\\\":false},{\\\"id\\\":\\\"extensions.ssh-remote+carbonate.default\\\",\\\"isHidden\\\":false},{\\\"id\\\":\\\"extensions.ssh-remote+carbonate.installed\\\",\\\"isHidden\\\":false},{\\\"id\\\":\\\"extensions.ssh-remote+carbonate.outdated\\\",\\\"isHidden\\\":false},{\\\"id\\\":\\\"extensions.local.default\\\",\\\"isHidden\\\":false},{\\\"id\\\":\\\"extensions.local.installed\\\",\\\"isHidden\\\":false},{\\\"id\\\":\\\"extensions.local.outdated\\\",\\\"isHidden\\\":false},{\\\"id\\\":\\\"extensions.remote.default\\\",\\\"isHidden\\\":false},{\\\"id\\\":\\\"extensions.remote.installed\\\",\\\"isHidden\\\":false},{\\\"id\\\":\\\"extensions.remote.outdated\\\",\\\"isHidden\\\":false},{\\\"id\\\":\\\"workbench.views.extensions.popular\\\",\\\"isHidden\\\":false},{\\\"id\\\":\\\"workbench.views.extensions.workspaceRecommendations\\\",\\\"isHidden\\\":false},{\\\"id\\\":\\\"workbench.views.extensions.installed\\\",\\\"isHidden\\\":false},{\\\"id\\\":\\\"workbench.views.extensions.otherRecommendations\\\",\\\"isHidden\\\":false},{\\\"id\\\":\\\"workbench.views.extensions.enabled\\\",\\\"isHidden\\\":true},{\\\"id\\\":\\\"workbench.views.extensions.disabled\\\",\\\"isHidden\\\":true},{\\\"id\\\":\\\"workbench.views.extensions.marketplace\\\",\\\"isHidden\\\":false},{\\\"id\\\":\\\"workbench.views.extensions.searchInstalled\\\",\\\"isHidden\\\":false},{\\\"id\\\":\\\"workbench.views.extensions.searchEnabled\\\",\\\"isHidden\\\":false},{\\\"id\\\":\\\"workbench.views.extensions.searchDisabled\\\",\\\"isHidden\\\":false},{\\\"id\\\":\\\"workbench.views.extensions.searchOutdated\\\",\\\"isHidden\\\":false},{\\\"id\\\":\\\"workbench.views.extensions.searchBuiltin\\\",\\\"isHidden\\\":false},{\\\"id\\\":\\\"workbench.views.extensions.builtinFeatureExtensions\\\",\\\"isHidden\\\":false},{\\\"id\\\":\\\"workbench.views.extensions.builtinThemeExtensions\\\",\\\"isHidden\\\":false},{\\\"id\\\":\\\"workbench.views.extensions.builtinProgrammingLanguageExtensions\\\",\\\"isHidden\\\":false}]\"},\"workbench.view.remote.state.hidden\":{\"version\":1,\"value\":\"[{\\\"id\\\":\\\"sshHosts\\\",\\\"isHidden\\\":false},{\\\"id\\\":\\\"~remote.helpPanel\\\",\\\"isHidden\\\":false},{\\\"id\\\":\\\"~remote.forwardedPorts\\\",\\\"isHidden\\\":false}]\"},\"workbench.view.search.state.hidden\":{\"version\":1,\"value\":\"[{\\\"id\\\":\\\"workbench.view.search\\\",\\\"isHidden\\\":false}]\"},\"workbench.view.sync.state.hidden\":{\"version\":1,\"value\":\"[{\\\"id\\\":\\\"workbench.views.sync.merges\\\",\\\"isHidden\\\":false},{\\\"id\\\":\\\"workbench.views.sync.remoteActivity\\\",\\\"isHidden\\\":false},{\\\"id\\\":\\\"workbench.views.sync.machines\\\",\\\"isHidden\\\":false},{\\\"id\\\":\\\"workbench.views.sync.localActivity\\\",\\\"isHidden\\\":true}]\"}}}"}